Metadata-Version: 2.1
Name: cfc-bsb
Version: 1.0.0
Summary: Get your localhost online and https - Ngrok Alternative
Home-page: https://github.com/Sphabsb2192/codes
Author: Coffin Codes V4
Author-email: sphabsb2192@gmail.com
Maintainer: BSB Developers
Maintainer-email: sphabsb2192@gmail.com
License: MIT
Keywords: Coffin Codes live localhost online https ngrok alternative
Platform: UNKNOWN
Classifier: Development Status :: 5 - Production/Stable
Classifier: Environment :: Web Environment
Classifier: Intended Audience :: Developers
Classifier: Operating System :: OS Independent
Classifier: Programming Language :: Python
Classifier: Programming Language :: Python :: 3
Classifier: Programming Language :: Python :: 3.6
Classifier: Programming Language :: Python :: 3.7
Classifier: Programming Language :: Python :: 3.8
Classifier: Programming Language :: Python :: 3.9
Requires-Python: >=3.6.1
